dargs/__init__.py
dargs/__main__.py
dargs/_test.py
dargs/_version.py
dargs/check.py
dargs/cli.py
dargs/dargs.py
dargs/json_schema.py
dargs/notebook.py
dargs/py.typed
dargs/sphinx.py
dargs-0.4.10.dist-info/LICENSE
dargs-0.4.10.dist-info/METADATA
dargs-0.4.10.dist-info/WHEEL
dargs-0.4.10.dist-info/entry_points.txt
dargs-0.4.10.dist-info/top_level.txt
dargs-0.4.10.dist-info/RECORD
