Metadata-Version: 2.1
Name: dargs
Version: 0.4.10
Summary: Process arguments for the deep modeling project.
Author: DeepModeling
Author-email: Yixiao Chen <yixiaoc@princeton.edu>
License:                    GNU LESSER GENERAL PUBLIC LICENSE
Project-URL: Homepage, https://github.com/deepmodeling/dargs
Project-URL: documentation, https://docs.deepmodeling.com/projects/dargs
Project-URL: repository, https://github.com/deepmodeling/dargs
Classifier: Programming Language :: Python :: 3.7
Classifier: License :: OSI Approved :: GNU Lesser General Public License v3 (LGPLv3)
Requires-Python: >=3.7
Provides-Extra: test
Provides-Extra: typecheck
License-File: LICENSE
